[
    {
        "name": "Bob",
        "email": "bobsmith42@gmail.com",
        "phone": "+79123456789"
    },
    {
        "name": "Clara",
        "email": "clara.jones@mail.ru",
        "phone": "+79011234567"
    },
    {
        "name": "Daniel",
        "email": "daniel.kim@example.com",
        "phone": "+79205551234"
    },
    {
        "name": "Eva",
        "email": "eva_love@gmail.com",
        "phone": "+79037654321"
    },
    {
        "name": "Frank",
        "email": "frank_the_tank@rambler.ru",
        "phone": "+79876543210"
    },
    {
        "name": "Grace",
        "email": "grace99@yandex.ru",
        "phone": "+79112223344"
    },
    {
        "name": "Henry",
        "email": "henry.potter@bk.ru",
        "phone": "+79034445566"
    },
    {
        "name": "Isabella",
        "email": "isa_bella@mail.com",
        "phone": "+79001112233"
    },
    {
        "name": "Jack",
        "email": "jack.black@gmail.com",
        "phone": "+79998887766"
    },
    {
        "name": "Karen",
        "email": "karen_moore@inbox.ru",
        "phone": "+79090001122"
    },
    {
        "name": "Liam",
        "email": "liam.turner@gmail.com",
        "phone": "+79010101010"
    },
    {
        "name": "Mia",
        "email": "mia_star@mail.ru",
        "phone": "+79021234567"
    },
    {
        "name": "Noah",
        "email": "noah.green@outlook.com",
        "phone": "+79130001122"
    },
    {
        "name": "Olivia",
        "email": "olivia.rose@yandex.ru",
        "phone": "+79075556644"
    },
    {
        "name": "Paul",
        "email": "paul.bright@bk.ru",
        "phone": "+79889990000"
    },
    {
        "name": "Quinn",
        "email": "quinn.zone@gmail.com",
        "phone": "+79000012345"
    },
    {
        "name": "Ruby",
        "email": "ruby_heart@mail.com",
        "phone": "+79081112233"
    },
    {
        "name": "Samuel",
        "email": "samuel.jackson@rambler.ru",
        "phone": "+79006667788"
    },
    {
        "name": "Tina",
        "email": "tina_sunshine@yandex.ru",
        "phone": "+79112220033"
    },
    {
        "name": "Victor",
        "email": "victor.kovalski@inbox.ru",
        "phone": "+79034345678"
    }
]
